notas_musicais/__init__.py
notas_musicais/acordes.py
notas_musicais/campo_harmonico.py
notas_musicais/cli.py
notas_musicais/escala.py
music_notas-0.1.0.dist-info/entry_points.txt
music_notas-0.1.0.dist-info/LICENSE
music_notas-0.1.0.dist-info/METADATA
music_notas-0.1.0.dist-info/WHEEL
music_notas-0.1.0.dist-info/RECORD
