Metadata-Version: 2.1
Name: music-notas
Version: 0.1.0
Summary: Notas musicais é um CLI para ajudar na formação de escalas, acordes e campos harmônicos
License: Beerware
Author: johonnes
Author-email: wjohonnes@gmail.com
Requires-Python: >=3.12,<4.0
Classifier: Development Status :: 5 - Production/Stable
Classifier: Environment :: Console
Classifier: License :: Other/Proprietary License
Classifier: Natural Language :: Portuguese (Brazilian)
Classifier: Programming Language :: Python :: 3
Classifier: Programming Language :: Python :: 3.12
Classifier: Topic :: Education
Requires-Dist: rich (>=13.8.1,<14.0.0)
Requires-Dist: typer (>=0.12.5,<0.13.0)
Project-URL: Bug Tracker, https://github.com/johonnes/music-notas/issues
Project-URL: Código, https://github.com/johonnes/music-notas
Project-URL: Documentação, https://music-notas.readthedocs.io/pt-br/latest/
